[
  {
    "이름": "박종범",
    "담당 업무": "현장",
    "출근 시간": "2025. 7. 11 7:29:24",
    "퇴근 시간": "2025. 7. 11 16:52:51",
    "근무시간(H:M)": "7시간 13분",
    "퇴근미체크": false,
    "날짜": "2025. 7. 11",
    "회사명": "BAT"
  },
  {
    "이름": "정인규",
    "담당 업무": "현장",
    "출근 시간": "2025. 7. 11 7:30:18",
    "퇴근 시간": "2025. 7. 11 17:00:16",
    "근무시간(H:M)": "7시간 20분",
    "퇴근미체크": false,
    "날짜": "2025. 7. 11",
    "회사명": "BAT"
  },
  {
    "이름": "황호",
    "담당 업무": "현장",
    "출근 시간": "2025. 7. 11 7:34:54",
    "퇴근 시간": "2025. 7. 11 17:01:41",
    "근무시간(H:M)": "7시간 22분",
    "퇴근미체크": false,
    "날짜": "2025. 7. 11",
    "회사명": "BAT"
  },
  {
    "이름": "김원동",
    "담당 업무": "현장",
    "출근 시간": "2025. 7. 11 7:40:04",
    "퇴근 시간": null,
    "근무시간(H:M)": "0시간 0분",
    "퇴근미체크": true,
    "날짜": "2025. 7. 11",
    "회사명": "BAT"
  },
  {
    "이름": "윤청용",
    "담당 업무": "현장",
    "출근 시간": "2025. 7. 11 7:42:03",
    "퇴근 시간": "2025. 7. 11 16:53:07",
    "근무시간(H:M)": "7시간 13분",
    "퇴근미체크": false,
    "날짜": "2025. 7. 11",
    "회사명": "BAT"
  },
  {
    "이름": "김군",
    "담당 업무": "현장",
    "출근 시간": "2025. 7. 11 7:43:49",
    "퇴근 시간": "2025. 7. 11 16:43:05",
    "근무시간(H:M)": "7시간 3분",
    "퇴근미체크": false,
    "날짜": "2025. 7. 11",
    "회사명": "BAT"
  },
  {
    "이름": "허용길",
    "담당 업무": "현장",
    "출근 시간": "2025. 7. 11 7:44:51",
    "퇴근 시간": "2025. 7. 11 16:40:11",
    "근무시간(H:M)": "7시간 0분",
    "퇴근미체크": false,
    "날짜": "2025. 7. 11",
    "회사명": "BAT"
  },
  {
    "이름": "채은철",
    "담당 업무": "현장",
    "출근 시간": "2025. 7. 11 7:44:56",
    "퇴근 시간": "2025. 7. 11 16:41:42",
    "근무시간(H:M)": "7시간 2분",
    "퇴근미체크": false,
    "날짜": "2025. 7. 11",
    "회사명": "BAT"
  },
  {
    "이름": "전성환",
    "담당 업무": "현장",
    "출근 시간": "2025. 7. 11 7:45:31",
    "퇴근 시간": null,
    "근무시간(H:M)": "0시간 0분",
    "퇴근미체크": true,
    "날짜": "2025. 7. 11",
    "회사명": "BAT"
  },
  {
    "이름": "최진우",
    "담당 업무": "현장",
    "출근 시간": "2025. 7. 11 7:53:45",
    "퇴근 시간": "2025. 7. 11 16:52:33",
    "근무시간(H:M)": "7시간 13분",
    "퇴근미체크": false,
    "날짜": "2025. 7. 11",
    "회사명": "BAT"
  },
  {
    "이름": "조동래",
    "담당 업무": "현장",
    "출근 시간": "2025. 7. 11 7:56:36",
    "퇴근 시간": "2025. 7. 11 16:53:03",
    "근무시간(H:M)": "7시간 13분",
    "퇴근미체크": false,
    "날짜": "2025. 7. 11",
    "회사명": "BAT"
  },
  {
    "이름": "간연웅",
    "담당 업무": "현장",
    "출근 시간": "2025. 7. 11 7:56:58",
    "퇴근 시간": "2025. 7. 11 16:52:05",
    "근무시간(H:M)": "7시간 12분",
    "퇴근미체크": false,
    "날짜": "2025. 7. 11",
    "회사명": "BAT"
  },
  {
    "이름": "임동국",
    "담당 업무": "현장",
    "출근 시간": "2025. 7. 11 7:57:40",
    "퇴근 시간": "2025. 7. 11 16:52:05",
    "근무시간(H:M)": "7시간 12분",
    "퇴근미체크": false,
    "날짜": "2025. 7. 11",
    "회사명": "BAT"
  },
  {
    "이름": "홍사현",
    "담당 업무": "현장",
    "출근 시간": "2025. 7. 11 7:58:38",
    "퇴근 시간": "2025. 7. 11 16:52:04",
    "근무시간(H:M)": "7시간 12분",
    "퇴근미체크": false,
    "날짜": "2025. 7. 11",
    "회사명": "BAT"
  },
  {
    "이름": "박호",
    "담당 업무": "현장",
    "출근 시간": "2025. 7. 11 8:05:36",
    "퇴근 시간": "2025. 7. 11 16:51:55",
    "근무시간(H:M)": "7시간 6분",
    "퇴근미체크": false,
    "날짜": "2025. 7. 11",
    "회사명": "BAT"
  },
  {
    "이름": "배홍범",
    "담당 업무": "현장",
    "출근 시간": "2025. 7. 11 8:20:27",
    "퇴근 시간": "2025. 7. 11 16:41:25",
    "근무시간(H:M)": "6시간 41분",
    "퇴근미체크": false,
    "날짜": "2025. 7. 11",
    "회사명": "BAT"
  },
  {
    "이름": "김춘동",
    "담당 업무": "현장",
    "출근 시간": "2025. 7. 11 8:38:17",
    "퇴근 시간": "2025. 7. 11 16:52:34",
    "근무시간(H:M)": "6시간 34분",
    "퇴근미체크": false,
    "날짜": "2025. 7. 11",
    "회사명": "BAT"
  },
  {
    "이름": "우미현",
    "담당 업무": "현장",
    "출근 시간": "2025. 7. 11 8:40:54",
    "퇴근 시간": "2025. 7. 11 17:01:31",
    "근무시간(H:M)": "6시간 41분",
    "퇴근미체크": false,
    "날짜": "2025. 7. 11",
    "회사명": "BAT"
  },
  {
    "이름": "우미정",
    "담당 업무": "현장",
    "출근 시간": "2025. 7. 11 8:51:23",
    "퇴근 시간": "2025. 7. 11 16:52:18",
    "근무시간(H:M)": "6시간 21분",
    "퇴근미체크": false,
    "날짜": "2025. 7. 11",
    "회사명": "BAT"
  }
]