[
  {
    "이름": "김범곤",
    "담당 업무": "현장",
    "출근 시간": "2025. 11. 27 7:20:51",
    "퇴근 시간": "2025. 11. 27 17:52:01",
    "근무시간(H:M)": "8시간 12분",
    "퇴근미체크": false,
    "날짜": "2025. 11. 27",
    "회사명": "BAT"
  },
  {
    "이름": "정인규",
    "담당 업무": "현장",
    "출근 시간": "2025. 11. 27 7:30:16",
    "퇴근 시간": "2025. 11. 27 17:00:38",
    "근무시간(H:M)": "7시간 21분",
    "퇴근미체크": false,
    "날짜": "2025. 11. 27",
    "회사명": "BAT"
  },
  {
    "이름": "박호",
    "담당 업무": "현장",
    "출근 시간": "2025. 11. 27 7:34:03",
    "퇴근 시간": "2025. 11. 27 16:50:05",
    "근무시간(H:M)": "7시간 10분",
    "퇴근미체크": false,
    "날짜": "2025. 11. 27",
    "회사명": "BAT"
  },
  {
    "이름": "김군",
    "담당 업무": "현장",
    "출근 시간": "2025. 11. 27 7:36:54",
    "퇴근 시간": "2025. 11. 27 16:37:43",
    "근무시간(H:M)": "6시간 58분",
    "퇴근미체크": false,
    "날짜": "2025. 11. 27",
    "회사명": "BAT"
  },
  {
    "이름": "간연웅",
    "담당 업무": "현장",
    "출근 시간": "2025. 11. 27 7:39:23",
    "퇴근 시간": "2025. 11. 27 19:17:44",
    "근무시간(H:M)": "8시간 38분",
    "퇴근미체크": false,
    "날짜": "2025. 11. 27",
    "회사명": "BAT"
  },
  {
    "이름": "김원동",
    "담당 업무": "현장",
    "출근 시간": "2025. 11. 27 7:40:38",
    "퇴근 시간": "2025. 11. 27 16:45:23",
    "근무시간(H:M)": "7시간 5분",
    "퇴근미체크": false,
    "날짜": "2025. 11. 27",
    "회사명": "BAT"
  },
  {
    "이름": "전성환",
    "담당 업무": "현장",
    "출근 시간": "2025. 11. 27 7:45:19",
    "퇴근 시간": "2025. 11. 27 16:42:12",
    "근무시간(H:M)": "7시간 2분",
    "퇴근미체크": false,
    "날짜": "2025. 11. 27",
    "회사명": "BAT"
  },
  {
    "이름": "허용길",
    "담당 업무": "현장",
    "출근 시간": "2025. 11. 27 7:48:18",
    "퇴근 시간": "2025. 11. 27 16:36:02",
    "근무시간(H:M)": "6시간 56분",
    "퇴근미체크": false,
    "날짜": "2025. 11. 27",
    "회사명": "BAT"
  },
  {
    "이름": "배홍범",
    "담당 업무": "현장",
    "출근 시간": "2025. 11. 27 7:50:58",
    "퇴근 시간": "2025. 11. 27 16:33:00",
    "근무시간(H:M)": "6시간 53분",
    "퇴근미체크": false,
    "날짜": "2025. 11. 27",
    "회사명": "BAT"
  },
  {
    "이름": "반경태",
    "담당 업무": "현장",
    "출근 시간": "2025. 11. 27 7:51:16",
    "퇴근 시간": "2025. 11. 27 16:45:11",
    "근무시간(H:M)": "7시간 5분",
    "퇴근미체크": false,
    "날짜": "2025. 11. 27",
    "회사명": "BAT"
  },
  {
    "이름": "조동래",
    "담당 업무": "현장",
    "출근 시간": "2025. 11. 27 7:54:15",
    "퇴근 시간": "2025. 11. 27 16:48:53",
    "근무시간(H:M)": "7시간 9분",
    "퇴근미체크": false,
    "날짜": "2025. 11. 27",
    "회사명": "BAT"
  },
  {
    "이름": "최진우",
    "담당 업무": "현장",
    "출근 시간": "2025. 11. 27 7:55:00",
    "퇴근 시간": null,
    "근무시간(H:M)": "0시간 0분",
    "퇴근미체크": true,
    "날짜": "2025. 11. 27",
    "회사명": "BAT"
  },
  {
    "이름": "박종범",
    "담당 업무": "현장",
    "출근 시간": "2025. 11. 27 7:55:32",
    "퇴근 시간": null,
    "근무시간(H:M)": "0시간 0분",
    "퇴근미체크": true,
    "날짜": "2025. 11. 27",
    "회사명": "BAT"
  },
  {
    "이름": "정대한",
    "담당 업무": "현장",
    "출근 시간": "2025. 11. 27 7:56:20",
    "퇴근 시간": "2025. 11. 27 17:19:12",
    "근무시간(H:M)": "7시간 39분",
    "퇴근미체크": false,
    "날짜": "2025. 11. 27",
    "회사명": "BAT"
  },
  {
    "이름": "홍사현",
    "담당 업무": "현장",
    "출근 시간": "2025. 11. 27 7:56:33",
    "퇴근 시간": "2025. 11. 27 16:44:27",
    "근무시간(H:M)": "7시간 4분",
    "퇴근미체크": false,
    "날짜": "2025. 11. 27",
    "회사명": "BAT"
  },
  {
    "이름": "채은철",
    "담당 업무": "현장",
    "출근 시간": "2025. 11. 27 7:56:53",
    "퇴근 시간": "2025. 11. 27 16:41:07",
    "근무시간(H:M)": "7시간 1분",
    "퇴근미체크": false,
    "날짜": "2025. 11. 27",
    "회사명": "BAT"
  },
  {
    "이름": "이영남",
    "담당 업무": "현장",
    "출근 시간": "2025. 11. 27 7:57:04",
    "퇴근 시간": null,
    "근무시간(H:M)": "0시간 0분",
    "퇴근미체크": true,
    "날짜": "2025. 11. 27",
    "회사명": "BAT"
  }
]