[
  {
    "이름": "박종범",
    "담당 업무": "현장",
    "출근 시간": "2025. 7. 18 7:22:38",
    "퇴근 시간": null,
    "근무시간(H:M)": "0시간 0분",
    "퇴근미체크": true,
    "날짜": "2025. 7. 18",
    "회사명": "BAT"
  },
  {
    "이름": "정인규",
    "담당 업무": "현장",
    "출근 시간": "2025. 7. 18 7:30:26",
    "퇴근 시간": null,
    "근무시간(H:M)": "0시간 0분",
    "퇴근미체크": true,
    "날짜": "2025. 7. 18",
    "회사명": "BAT"
  },
  {
    "이름": "박호",
    "담당 업무": "현장",
    "출근 시간": "2025. 7. 18 7:31:46",
    "퇴근 시간": null,
    "근무시간(H:M)": "0시간 0분",
    "퇴근미체크": true,
    "날짜": "2025. 7. 18",
    "회사명": "BAT"
  },
  {
    "이름": "채은철",
    "담당 업무": "현장",
    "출근 시간": "2025. 7. 18 7:38:12",
    "퇴근 시간": null,
    "근무시간(H:M)": "0시간 0분",
    "퇴근미체크": true,
    "날짜": "2025. 7. 18",
    "회사명": "BAT"
  },
  {
    "이름": "김군",
    "담당 업무": "현장",
    "출근 시간": "2025. 7. 18 7:38:47",
    "퇴근 시간": null,
    "근무시간(H:M)": "0시간 0분",
    "퇴근미체크": true,
    "날짜": "2025. 7. 18",
    "회사명": "BAT"
  },
  {
    "이름": "김원동",
    "담당 업무": "현장",
    "출근 시간": "2025. 7. 18 7:45:04",
    "퇴근 시간": null,
    "근무시간(H:M)": "0시간 0분",
    "퇴근미체크": true,
    "날짜": "2025. 7. 18",
    "회사명": "BAT"
  },
  {
    "이름": "전성환",
    "담당 업무": "현장",
    "출근 시간": "2025. 7. 18 7:45:23",
    "퇴근 시간": null,
    "근무시간(H:M)": "0시간 0분",
    "퇴근미체크": true,
    "날짜": "2025. 7. 18",
    "회사명": "BAT"
  },
  {
    "이름": "황호",
    "담당 업무": "현장",
    "출근 시간": "2025. 7. 18 7:46:35",
    "퇴근 시간": null,
    "근무시간(H:M)": "0시간 0분",
    "퇴근미체크": true,
    "날짜": "2025. 7. 18",
    "회사명": "BAT"
  },
  {
    "이름": "윤청용",
    "담당 업무": "현장",
    "출근 시간": "2025. 7. 18 7:47:50",
    "퇴근 시간": null,
    "근무시간(H:M)": "0시간 0분",
    "퇴근미체크": true,
    "날짜": "2025. 7. 18",
    "회사명": "BAT"
  },
  {
    "이름": "허용길",
    "담당 업무": "현장",
    "출근 시간": "2025. 7. 18 7:48:22",
    "퇴근 시간": null,
    "근무시간(H:M)": "0시간 0분",
    "퇴근미체크": true,
    "날짜": "2025. 7. 18",
    "회사명": "BAT"
  },
  {
    "이름": "간연웅",
    "담당 업무": "현장",
    "출근 시간": "2025. 7. 18 7:48:41",
    "퇴근 시간": null,
    "근무시간(H:M)": "0시간 0분",
    "퇴근미체크": true,
    "날짜": "2025. 7. 18",
    "회사명": "BAT"
  },
  {
    "이름": "조동래",
    "담당 업무": "현장",
    "출근 시간": "2025. 7. 18 7:54:53",
    "퇴근 시간": null,
    "근무시간(H:M)": "0시간 0분",
    "퇴근미체크": true,
    "날짜": "2025. 7. 18",
    "회사명": "BAT"
  },
  {
    "이름": "홍사현",
    "담당 업무": "현장",
    "출근 시간": "2025. 7. 18 7:57:30",
    "퇴근 시간": null,
    "근무시간(H:M)": "0시간 0분",
    "퇴근미체크": true,
    "날짜": "2025. 7. 18",
    "회사명": "BAT"
  },
  {
    "이름": "배홍범",
    "담당 업무": "현장",
    "출근 시간": "2025. 7. 18 7:59:23",
    "퇴근 시간": null,
    "근무시간(H:M)": "0시간 0분",
    "퇴근미체크": true,
    "날짜": "2025. 7. 18",
    "회사명": "BAT"
  },
  {
    "이름": "우미현",
    "담당 업무": "현장",
    "출근 시간": "2025. 7. 18 8:34:31",
    "퇴근 시간": "2025. 7. 18 08:34:40",
    "근무시간(H:M)": "0시간 0분",
    "퇴근미체크": false,
    "날짜": "2025. 7. 18",
    "회사명": "BAT"
  },
  {
    "이름": "김춘동",
    "담당 업무": "현장",
    "출근 시간": "2025. 7. 18 8:42:42",
    "퇴근 시간": null,
    "근무시간(H:M)": "0시간 0분",
    "퇴근미체크": true,
    "날짜": "2025. 7. 18",
    "회사명": "BAT"
  },
  {
    "이름": "우미정",
    "담당 업무": "현장",
    "출근 시간": "2025. 7. 18 8:51:07",
    "퇴근 시간": null,
    "근무시간(H:M)": "0시간 0분",
    "퇴근미체크": true,
    "날짜": "2025. 7. 18",
    "회사명": "BAT"
  }
]