[
  {
    "이름": "김군",
    "담당 업무": "현장",
    "출근 시간": "2025. 9. 4 7:28:56",
    "퇴근 시간": null,
    "근무시간(H:M)": "0시간 0분",
    "퇴근미체크": true,
    "날짜": "2025. 9. 4",
    "회사명": "BAT"
  },
  {
    "이름": "정인규",
    "담당 업무": "현장",
    "출근 시간": "2025. 9. 4 7:30:33",
    "퇴근 시간": "2025. 9. 4 17:00:23",
    "근무시간(H:M)": "7시간 20분",
    "퇴근미체크": false,
    "날짜": "2025. 9. 4",
    "회사명": "BAT"
  },
  {
    "이름": "박종범",
    "담당 업무": "현장",
    "출근 시간": "2025. 9. 4 7:32:59",
    "퇴근 시간": null,
    "근무시간(H:M)": "0시간 0분",
    "퇴근미체크": true,
    "날짜": "2025. 9. 4",
    "회사명": "BAT"
  },
  {
    "이름": "박호",
    "담당 업무": "현장",
    "출근 시간": "2025. 9. 4 7:40:16",
    "퇴근 시간": null,
    "근무시간(H:M)": "0시간 0분",
    "퇴근미체크": true,
    "날짜": "2025. 9. 4",
    "회사명": "BAT"
  },
  {
    "이름": "전성환",
    "담당 업무": "현장",
    "출근 시간": "2025. 9. 4 7:45:27",
    "퇴근 시간": null,
    "근무시간(H:M)": "0시간 0분",
    "퇴근미체크": true,
    "날짜": "2025. 9. 4",
    "회사명": "BAT"
  },
  {
    "이름": "윤청용",
    "담당 업무": "현장",
    "출근 시간": "2025. 9. 4 7:47:54",
    "퇴근 시간": null,
    "근무시간(H:M)": "0시간 0분",
    "퇴근미체크": true,
    "날짜": "2025. 9. 4",
    "회사명": "BAT"
  },
  {
    "이름": "황호",
    "담당 업무": "현장",
    "출근 시간": "2025. 9. 4 7:48:25",
    "퇴근 시간": null,
    "근무시간(H:M)": "0시간 0분",
    "퇴근미체크": true,
    "날짜": "2025. 9. 4",
    "회사명": "BAT"
  },
  {
    "이름": "간연웅",
    "담당 업무": "현장",
    "출근 시간": "2025. 9. 4 7:48:43",
    "퇴근 시간": null,
    "근무시간(H:M)": "0시간 0분",
    "퇴근미체크": true,
    "날짜": "2025. 9. 4",
    "회사명": "BAT"
  },
  {
    "이름": "배홍범",
    "담당 업무": "현장",
    "출근 시간": "2025. 9. 4 7:49:25",
    "퇴근 시간": null,
    "근무시간(H:M)": "0시간 0분",
    "퇴근미체크": true,
    "날짜": "2025. 9. 4",
    "회사명": "BAT"
  },
  {
    "이름": "조동래",
    "담당 업무": "현장",
    "출근 시간": "2025. 9. 4 7:50:27",
    "퇴근 시간": null,
    "근무시간(H:M)": "0시간 0분",
    "퇴근미체크": true,
    "날짜": "2025. 9. 4",
    "회사명": "BAT"
  },
  {
    "이름": "정대한",
    "담당 업무": "현장",
    "출근 시간": "2025. 9. 4 7:51:14",
    "퇴근 시간": "2025. 9. 4 17:19:46",
    "근무시간(H:M)": "7시간 40분",
    "퇴근미체크": false,
    "날짜": "2025. 9. 4",
    "회사명": "BAT"
  },
  {
    "이름": "최진우",
    "담당 업무": "현장",
    "출근 시간": "2025. 9. 4 7:53:27",
    "퇴근 시간": null,
    "근무시간(H:M)": "0시간 0분",
    "퇴근미체크": true,
    "날짜": "2025. 9. 4",
    "회사명": "BAT"
  },
  {
    "이름": "허용길",
    "담당 업무": "현장",
    "출근 시간": "2025. 9. 4 7:53:50",
    "퇴근 시간": null,
    "근무시간(H:M)": "0시간 0분",
    "퇴근미체크": true,
    "날짜": "2025. 9. 4",
    "회사명": "BAT"
  },
  {
    "이름": "심영수",
    "담당 업무": "현장",
    "출근 시간": "2025. 9. 4 7:55:34",
    "퇴근 시간": "2025. 9. 4 16:53:20",
    "근무시간(H:M)": "7시간 13분",
    "퇴근미체크": false,
    "날짜": "2025. 9. 4",
    "회사명": "BAT"
  },
  {
    "이름": "홍사현",
    "담당 업무": "현장",
    "출근 시간": "2025. 9. 4 7:59:35",
    "퇴근 시간": null,
    "근무시간(H:M)": "0시간 0분",
    "퇴근미체크": true,
    "날짜": "2025. 9. 4",
    "회사명": "BAT"
  },
  {
    "이름": "이영남",
    "담당 업무": "현장",
    "출근 시간": "2025. 9. 4 8:05:52",
    "퇴근 시간": null,
    "근무시간(H:M)": "0시간 0분",
    "퇴근미체크": true,
    "날짜": "2025. 9. 4",
    "회사명": "BAT"
  },
  {
    "이름": "우미현",
    "담당 업무": "현장",
    "출근 시간": "2025. 9. 4 8:23:06",
    "퇴근 시간": "2025. 9. 4 16:56:20",
    "근무시간(H:M)": "6시간 53분",
    "퇴근미체크": false,
    "날짜": "2025. 9. 4",
    "회사명": "BAT"
  },
  {
    "이름": "김춘동",
    "담당 업무": "현장",
    "출근 시간": "2025. 9. 4 8:43:56",
    "퇴근 시간": "2025. 9. 4 17:07:59",
    "근무시간(H:M)": "6시간 44분",
    "퇴근미체크": false,
    "날짜": "2025. 9. 4",
    "회사명": "BAT"
  },
  {
    "이름": "우미정",
    "담당 업무": "현장",
    "출근 시간": "2025. 9. 4 8:45:13",
    "퇴근 시간": "2025. 9. 4 17:00:01",
    "근무시간(H:M)": "6시간 35분",
    "퇴근미체크": false,
    "날짜": "2025. 9. 4",
    "회사명": "BAT"
  }
]