[
  {
    "이름": "정용진",
    "담당 업무": "현장",
    "출근 시간": "2025. 8. 25 7:17:25",
    "퇴근 시간": null,
    "근무시간(H:M)": "0시간 0분",
    "퇴근미체크": true,
    "날짜": "2025. 8. 25",
    "회사명": "C&A"
  },
  {
    "이름": "김도연",
    "담당 업무": "현장",
    "출근 시간": "2025. 8. 25 7:23:26",
    "퇴근 시간": null,
    "근무시간(H:M)": "0시간 0분",
    "퇴근미체크": true,
    "날짜": "2025. 8. 25",
    "회사명": "C&A"
  },
  {
    "이름": "김인욱",
    "담당 업무": "현장",
    "출근 시간": "2025. 8. 25 7:29:31",
    "퇴근 시간": "2025. 8. 25 07:58:58",
    "근무시간(H:M)": "0시간 0분",
    "퇴근미체크": false,
    "날짜": "2025. 8. 25",
    "회사명": "C&A"
  },
  {
    "이름": "장연호",
    "담당 업무": "현장",
    "출근 시간": "2025. 8. 25 7:38:47",
    "퇴근 시간": null,
    "근무시간(H:M)": "0시간 0분",
    "퇴근미체크": true,
    "날짜": "2025. 8. 25",
    "회사명": "C&A"
  },
  {
    "이름": "김우람",
    "담당 업무": "본사",
    "출근 시간": "2025. 8. 25 7:40:47",
    "퇴근 시간": null,
    "근무시간(H:M)": "0시간 0분",
    "퇴근미체크": true,
    "날짜": "2025. 8. 25",
    "회사명": "C&A"
  },
  {
    "이름": "조성호",
    "담당 업무": "현장",
    "출근 시간": "2025. 8. 25 7:42:34",
    "퇴근 시간": null,
    "근무시간(H:M)": "0시간 0분",
    "퇴근미체크": true,
    "날짜": "2025. 8. 25",
    "회사명": "C&A"
  },
  {
    "이름": "박은혜",
    "담당 업무": "본사",
    "출근 시간": "2025. 8. 25 7:43:30",
    "퇴근 시간": null,
    "근무시간(H:M)": "0시간 0분",
    "퇴근미체크": true,
    "날짜": "2025. 8. 25",
    "회사명": "C&A"
  },
  {
    "이름": "백상걸",
    "담당 업무": "현장",
    "출근 시간": "2025. 8. 25 7:47:11",
    "퇴근 시간": "2025. 8. 25 17:11:38",
    "근무시간(H:M)": "7시간 32분",
    "퇴근미체크": false,
    "날짜": "2025. 8. 25",
    "회사명": "C&A"
  },
  {
    "이름": "정지성",
    "담당 업무": "현장",
    "출근 시간": "2025. 8. 25 7:50:22",
    "퇴근 시간": null,
    "근무시간(H:M)": "0시간 0분",
    "퇴근미체크": true,
    "날짜": "2025. 8. 25",
    "회사명": "C&A"
  },
  {
    "이름": "성길용",
    "담당 업무": "현장",
    "출근 시간": "2025. 8. 25 7:51:46",
    "퇴근 시간": null,
    "근무시간(H:M)": "0시간 0분",
    "퇴근미체크": true,
    "날짜": "2025. 8. 25",
    "회사명": "C&A"
  },
  {
    "이름": "윤문빈",
    "담당 업무": "현장",
    "출근 시간": "2025. 8. 25 7:54:09",
    "퇴근 시간": null,
    "근무시간(H:M)": "0시간 0분",
    "퇴근미체크": true,
    "날짜": "2025. 8. 25",
    "회사명": "C&A"
  },
  {
    "이름": "임영대",
    "담당 업무": "본사CHI_2",
    "출근 시간": "2025. 8. 25 7:54:46",
    "퇴근 시간": null,
    "근무시간(H:M)": "0시간 0분",
    "퇴근미체크": true,
    "날짜": "2025. 8. 25",
    "회사명": "C&A"
  },
  {
    "이름": "이성훈",
    "담당 업무": "본사",
    "출근 시간": "2025. 8. 25 7:55:35",
    "퇴근 시간": null,
    "근무시간(H:M)": "0시간 0분",
    "퇴근미체크": true,
    "날짜": "2025. 8. 25",
    "회사명": "C&A"
  },
  {
    "이름": "라경숙",
    "담당 업무": "본사CHI_2",
    "출근 시간": "2025. 8. 25 7:55:36",
    "퇴근 시간": "2025. 8. 25 16:56:10",
    "근무시간(H:M)": "7시간 16분",
    "퇴근미체크": false,
    "날짜": "2025. 8. 25",
    "회사명": "C&A"
  },
  {
    "이름": "이우성",
    "담당 업무": "본사",
    "출근 시간": "2025. 8. 25 7:56:30",
    "퇴근 시간": null,
    "근무시간(H:M)": "0시간 0분",
    "퇴근미체크": true,
    "날짜": "2025. 8. 25",
    "회사명": "C&A"
  },
  {
    "이름": "한상준",
    "담당 업무": "본사CHI_2",
    "출근 시간": "2025. 8. 25 7:57:10",
    "퇴근 시간": "2025. 8. 25 17:00:11",
    "근무시간(H:M)": "7시간 20분",
    "퇴근미체크": false,
    "날짜": "2025. 8. 25",
    "회사명": "C&A"
  },
  {
    "이름": "이태희",
    "담당 업무": "본사CHI_1",
    "출근 시간": "2025. 8. 25 7:57:36",
    "퇴근 시간": null,
    "근무시간(H:M)": "0시간 0분",
    "퇴근미체크": true,
    "날짜": "2025. 8. 25",
    "회사명": "C&A"
  },
  {
    "이름": "박새벽",
    "담당 업무": "현장",
    "출근 시간": "2025. 8. 25 7:57:42",
    "퇴근 시간": null,
    "근무시간(H:M)": "0시간 0분",
    "퇴근미체크": true,
    "날짜": "2025. 8. 25",
    "회사명": "C&A"
  },
  {
    "이름": "홍수희",
    "담당 업무": "본사",
    "출근 시간": "2025. 8. 25 7:58:22",
    "퇴근 시간": null,
    "근무시간(H:M)": "0시간 0분",
    "퇴근미체크": true,
    "날짜": "2025. 8. 25",
    "회사명": "C&A"
  },
  {
    "이름": "김도형",
    "담당 업무": "본사",
    "출근 시간": "2025. 8. 25 8:00:32",
    "퇴근 시간": null,
    "근무시간(H:M)": "0시간 0분",
    "퇴근미체크": true,
    "날짜": "2025. 8. 25",
    "회사명": "C&A"
  },
  {
    "이름": "박준성",
    "담당 업무": "본사CHI_2",
    "출근 시간": "2025. 8. 25 8:13:56",
    "퇴근 시간": null,
    "근무시간(H:M)": "0시간 0분",
    "퇴근미체크": true,
    "날짜": "2025. 8. 25",
    "회사명": "C&A"
  },
  {
    "이름": "임영목",
    "담당 업무": "본사CHI_2",
    "출근 시간": "2025. 8. 25 8:34:59",
    "퇴근 시간": null,
    "근무시간(H:M)": "0시간 0분",
    "퇴근미체크": true,
    "날짜": "2025. 8. 25",
    "회사명": "C&A"
  },
  {
    "이름": "이영찬",
    "담당 업무": "본사CHI_2",
    "출근 시간": "2025. 8. 25 10:02:15",
    "퇴근 시간": null,
    "근무시간(H:M)": "0시간 0분",
    "퇴근미체크": true,
    "날짜": "2025. 8. 25",
    "회사명": "C&A"
  },
  {
    "이름": "박수현",
    "담당 업무": "현장",
    "출근 시간": "2025. 8. 25 17:11:28",
    "퇴근 시간": null,
    "근무시간(H:M)": "0시간 0분",
    "퇴근미체크": true,
    "날짜": "2025. 8. 25",
    "회사명": "C&A"
  }
]